README.rst
setup.py
uscrape/__init__.py
uscrape.egg-info/PKG-INFO
uscrape.egg-info/SOURCES.txt
uscrape.egg-info/dependency_links.txt
uscrape.egg-info/requires.txt
uscrape.egg-info/top_level.txt