Metadata-Version: 1.1
Name: uscrape
Version: 0.4
Summary: A set of commonly used functions for small scrapers.
Home-page: https://github.com/zejn/uscrape
Author: Gašper Žejn
Author-email: zejn@owca.info
License: UNKNOWN
Platform: UNKNOWN
Classifier: Development Status :: 4 - Beta
Classifier: Intended Audience :: Developers
Classifier: License :: OSI Approved :: MIT License
Classifier: Operating System :: OS Independent
Classifier: Programming Language :: Python
